planoai/__init__.py
planoai/config_generator.py
planoai/consts.py
planoai/core.py
planoai/docker_cli.py
planoai/main.py
planoai/targets.py
planoai/utils.py
planoai-0.4.3.dist-info/METADATA
planoai-0.4.3.dist-info/WHEEL
planoai-0.4.3.dist-info/entry_points.txt
planoai-0.4.3.dist-info/RECORD
