Metadata-Version: 2.4
Name: planoai
Version: 0.4.3
Summary: Python-based CLI tool to manage Plano.
Author: Katanemo Labs, Inc.
Requires-Python: >=3.10
Requires-Dist: click<9.0.0,>=8.1.7
Requires-Dist: jinja2<4.0.0,>=3.1.4
Requires-Dist: jsonschema<5.0.0,>=4.23.0
Requires-Dist: pyyaml<7.0.0,>=6.0.2
Requires-Dist: requests<3.0.0,>=2.31.0
Provides-Extra: dev
Requires-Dist: pytest<9.0.0,>=8.4.1; extra == 'dev'
